{
  "db_name": "PostgreSQL",
  "query": "\n        UPDATE kagzi.workflow_runs\n        SET status = 'PENDING',\n            locked_by = NULL,\n            available_at = NOW() + ($2 * INTERVAL '1 millisecond')\n        WHERE run_id = $1 AND status = 'RUNNING'\n        RETURNING namespace_id, task_queue, workflow_type\n        ",
  "describe": {
    "columns": [
      {
        "ordinal": 0,
        "name": "namespace_id",
        "type_info": "Text"
      },
      {
        "ordinal": 1,
        "name": "task_queue",
        "type_info": "Text"
      },
      {
        "ordinal": 2,
        "name": "workflow_type",
        "type_info": "Text"
      }
    ],
    "parameters": {
      "Left": [
        "Uuid",
        "Float8"
      ]
    },
    "nullable": [
      false,
      false,
      false
    ]
  },
  "hash": "930318f70e1b1c79c7d74f3cdd29b1bd1b235bb43c1451f3be59ef340dcccae5"
}
